framebot/__init__.py
framebot/__main__.py
framebot/framebots.py
framebot/model.py
framebot/plugins.py
framebot/social.py
framebot/utils.py
framebot/migration/__init__.py
framebot/migration/__main__.py
framebot/migration/migrate.py
framebot/resources/config.ini
pyframebot-1.1.8.dist-info/LICENSE
pyframebot-1.1.8.dist-info/METADATA
pyframebot-1.1.8.dist-info/WHEEL
pyframebot-1.1.8.dist-info/entry_points.txt
pyframebot-1.1.8.dist-info/top_level.txt
pyframebot-1.1.8.dist-info/RECORD
