Metadata-Version: 2.1
Name: pyframebot
Version: 1.1.8
Summary: A frame-posting bot for Facebook pages
Author-email: TheCodingBob <vey90@live.it>
License: GNU GENERAL PUBLIC LICENSE
Project-URL: Homepage, https://github.com/thecodingbob/framebot
Keywords: bot,facebook,everyframeinorder,frame,order
Classifier: Programming Language :: Python
Classifier: Programming Language :: Python :: 3
Requires-Python: >=3.7
License-File: LICENSE
Requires-Dist: python-facebook-api
Requires-Dist: Pillow (>=9.4.0)
Requires-Dist: jsonpickle
Requires-Dist: python-slugify
